aa_intercom/__init__.py
aa_intercom/admin.py
aa_intercom/celery.py
aa_intercom/exceptions.py
aa_intercom/mixins.py
aa_intercom/models.py
aa_intercom/signals.py
aa_intercom/tasks.py
aa_intercom/utils.py
aa_intercom/management/__init__.py
aa_intercom/management/commands/__init__.py
aa_intercom/management/commands/resend_intercom_events.py
aa_intercom/migrations/0001_initial.py
aa_intercom/migrations/__init__.py
aa_intercom/tests/__init__.py
aa_intercom/tests/test_base.py
aa_intercom/tests/test_commands.py
aa_intercom/tests/test_utils.py
aa_intercom-1.0.1.dist-info/DESCRIPTION.rst
aa_intercom-1.0.1.dist-info/METADATA
aa_intercom-1.0.1.dist-info/RECORD
aa_intercom-1.0.1.dist-info/WHEEL
aa_intercom-1.0.1.dist-info/metadata.json
aa_intercom-1.0.1.dist-info/top_level.txt
