Metadata-Version: 2.0
Name: aa-intercom
Version: 1.0.1
Summary: Django integration for Intercom API
Home-page: https://github.com/ArabellaTech/aa-intercom
Author: Jacek Ostanski
Author-email: jacek@arabel.la
License: MIT
Platform: UNKNOWN
Classifier: Development Status :: 3 - Alpha
Classifier: Environment :: Web Environment
Classifier: Framework :: Django
Classifier: Intended Audience :: Developers
Classifier: Operating System :: OS Independent
Classifier: Programming Language :: Python
Classifier: Programming Language :: Python :: 2.7
Classifier: Programming Language :: Python :: 3.4
Classifier: Programming Language :: Python :: 3.5
Classifier: Programming Language :: Python :: 3.6
Classifier: Topic :: Internet :: WWW/HTTP
Requires-Dist: celery (>=4.0.2)
Requires-Dist: django-jsonfield (>=1.0.1)
Requires-Dist: python-intercom (>=3.1.0)
